{
  "components": {
    "B1": {
      "footprint": "battery-placeholder", 
      "layer": "bottom", 
      "location": [
        -9.313811, 
        0.154315
      ], 
      "rotate": 180, 
      "show": true, 
      "silkscreen": {
        "refdef": {
          "location": [
            0, 
            0
          ]
        }
      }
    }, 
    "C1": {
      "footprint": "0805-cap", 
      "layer": "top", 
      "location": [
        -31.806824, 
        15.601365
      ], 
      "rotate": 0, 
      "show": true, 
      "silkscreen": {
        "refdef": {
          "location": [
            0, 
            0
          ]
        }
      }
    }, 
    "C2": {
      "footprint": "0805-cap", 
      "layer": "top", 
      "location": [
        -10.681661, 
        15.601365
      ], 
      "rotate": 0, 
      "show": true, 
      "silkscreen": {
        "refdef": {
          "location": [
            0, 
            0
          ]
        }
      }
    }, 
    "C3": {
      "footprint": "0805-cap", 
      "layer": "top", 
      "location": [
        -43.710642, 
        18.138665
      ], 
      "rotate": 0, 
      "show": true, 
      "silkscreen": {
        "refdef": {
          "location": [
            -0.37353, 
            0
          ]
        }
      }
    }, 
    "C4": {
      "footprint": "0805-cap", 
      "layer": "top", 
      "location": [
        -31.853553, 
        13.064063
      ], 
      "rotate": 0, 
      "show": true, 
      "silkscreen": {
        "refdef": {
          "location": [
            0, 
            0
          ]
        }
      }
    }, 
    "C5": {
      "footprint": "0805-cap", 
      "layer": "top", 
      "location": [
        -10.650184, 
        -14.846277
      ], 
      "rotate": 0, 
      "show": true, 
      "silkscreen": {
        "refdef": {
          "location": [
            0, 
            0
          ]
        }
      }
    }, 
    "C51": {
      "footprint": "0805-cap", 
      "layer": "top", 
      "location": [
        -43.757371, 
        0.747663
      ], 
      "rotate": 0, 
      "show": true, 
      "silkscreen": {
        "refdef": {
          "location": [
            0, 
            0
          ]
        }
      }
    }, 
    "C55": {
      "footprint": "0805-cap", 
      "layer": "top", 
      "location": [
        -10.681661, 
        -9.77167
      ], 
      "rotate": 0, 
      "show": true, 
      "silkscreen": {
        "refdef": {
          "location": [
            0, 
            0
          ]
        }
      }
    }, 
    "C61": {
      "footprint": "0805-cap", 
      "layer": "top", 
      "location": [
        -91.56261, 
        -3.442144
      ], 
      "rotate": 0, 
      "show": true, 
      "silkscreen": {
        "refdef": {
          "location": [
            0, 
            0
          ]
        }
      }
    }, 
    "C71": {
      "footprint": "0805-cap", 
      "layer": "top", 
      "location": [
        -43.757371, 
        -1.635513
      ], 
      "rotate": 0, 
      "show": true, 
      "silkscreen": {
        "refdef": {
          "location": [
            0, 
            0
          ]
        }
      }
    }, 
    "C81": {
      "footprint": "0805-cap", 
      "layer": "top", 
      "location": [
        -92.403731, 
        5.389631
      ], 
      "rotate": 0, 
      "show": true, 
      "silkscreen": {
        "refdef": {
          "location": [
            0, 
            0
          ]
        }
      }
    }, 
    "IC1": {
      "footprint": "TPA301D-SOIC8", 
      "layer": "top", 
      "location": [
        -21.853332, 
        15.921447
      ], 
      "rotate": 0, 
      "show": true
    }, 
    "IC2": {
      "footprint": "MKE04Z8VWJ4-SOIC20", 
      "layer": "top", 
      "location": [
        -21.853332, 
        1.587401
      ], 
      "rotate": 180, 
      "show": true
    }, 
    "IC3": {
      "footprint": "LDO-fixed-TSOT-23-5", 
      "layer": "top", 
      "location": [
        -47.767916, 
        -0.022409
      ], 
      "rotate": 0, 
      "show": true
    }, 
    "IC4": {
      "footprint": "dual-nFET-SOT363", 
      "layer": "top", 
      "location": [
        -4.705088, 
        -13.284445
      ], 
      "rotate": 0, 
      "show": true
    }, 
    "J1": {
      "footprint": "1x4-2p54-stag", 
      "layer": "top", 
      "location": [
        8.172962, 
        21.128888
      ], 
      "rotate": 0, 
      "show": true, 
      "silkscreen": {
        "refdef": {
          "location": [
            0, 
            0
          ]
        }
      }
    }, 
    "J2": {
      "footprint": "1x6-2p54-stag", 
      "layer": "top", 
      "location": [
        -49.351108, 
        10.724445
      ], 
      "rotate": 90, 
      "show": true, 
      "silkscreen": {
        "refdef": {
          "location": [
            0, 
            0
          ]
        }
      }
    }, 
    "J3": {
      "footprint": "solder-blob-jumper", 
      "layer": "bottom", 
      "location": [
        -91.27707, 
        -17.197672
      ], 
      "rotate": 0, 
      "show": true, 
      "silkscreen": {
        "refdef": {
          "location": [
            0, 
            0
          ]
        }
      }
    }, 
    "J33": {
      "footprint": "interface-holes", 
      "layer": "top", 
      "location": [
        33.471123, 
        0
      ], 
      "rotate": 0, 
      "show": true, 
      "silkscreen": {
        "refdef": {
          "location": [
            0, 
            0
          ]
        }
      }
    }, 
    "J34": {
      "footprint": "interface-holes", 
      "layer": "top", 
      "location": [
        24.600004, 
        0
      ], 
      "rotate": 0, 
      "show": true, 
      "silkscreen": {
        "refdef": {
          "location": [
            0, 
            0
          ]
        }
      }
    }, 
    "J4": {
      "footprint": "1x6-2p54-stag", 
      "layer": "top", 
      "location": [
        -49.351108, 
        -10.724445
      ], 
      "rotate": 90, 
      "show": true, 
      "silkscreen": {
        "refdef": {
          "location": [
            0, 
            0
          ]
        }
      }
    }, 
    "J5": {
      "footprint": "microSD-molex-105162-001", 
      "layer": "top", 
      "location": [
        -21.853332, 
        -17.728305
      ], 
      "rotate": 0, 
      "show": true, 
      "silkscreen": {
        "refdef": {
          "location": [
            0, 
            0
          ]
        }
      }
    }, 
    "J6": {
      "footprint": "1x4-2p54-stag", 
      "layer": "top", 
      "location": [
        8.172962, 
        -21.128888
      ], 
      "rotate": 0, 
      "show": true, 
      "silkscreen": {
        "refdef": {
          "location": [
            0, 
            0
          ]
        }
      }
    }, 
    "LED1": {
      "footprint": "led-1206", 
      "layer": "bottom", 
      "location": [
        -118.74665, 
        8.064444
      ], 
      "rotate": 0, 
      "show": false, 
      "silkscreen": {
        "refdef": {
          "show": false
        }
      }
    }, 
    "LED2": {
      "footprint": "led-5mm", 
      "layer": "top", 
      "location": [
        42.330152, 
        8.941977
      ], 
      "rotate": 0, 
      "show": true, 
      "silkscreen": {
        "refdef": {
          "location": [
            0, 
            0
          ]
        }
      }
    }, 
    "LED3": {
      "footprint": "led-5mm", 
      "layer": "top", 
      "location": [
        42.58832, 
        -8.527546
      ], 
      "rotate": 0, 
      "show": true, 
      "silkscreen": {
        "refdef": {
          "location": [
            0, 
            0
          ]
        }
      }
    }, 
    "R1": {
      "footprint": "0805", 
      "layer": "top", 
      "location": [
        -31.821886, 
        18.139324
      ], 
      "rotate": 0, 
      "show": true, 
      "silkscreen": {
        "refdef": {
          "location": [
            0, 
            0
          ]
        }
      }
    }, 
    "R10": {
      "footprint": "0805", 
      "layer": "top", 
      "location": [
        -37.766265, 
        10.526758
      ], 
      "rotate": 0, 
      "show": true, 
      "silkscreen": {
        "refdef": {
          "location": [
            2.971559, 
            0
          ]
        }
      }
    }, 
    "R11": {
      "footprint": "0805", 
      "layer": "top", 
      "location": [
        -10.681661, 
        10.527418
      ], 
      "rotate": 0, 
      "show": true, 
      "silkscreen": {
        "refdef": {
          "location": [
            0, 
            0
          ]
        }
      }
    }, 
    "R12": {
      "footprint": "0805", 
      "layer": "top", 
      "location": [
        -37.766265, 
        7.989454
      ], 
      "rotate": 0, 
      "show": true, 
      "silkscreen": {
        "refdef": {
          "location": [
            2.964601, 
            0
          ]
        }
      }
    }, 
    "R13": {
      "footprint": "0805", 
      "layer": "top", 
      "location": [
        -43.710642, 
        10.526758
      ], 
      "rotate": 0, 
      "show": true, 
      "silkscreen": {
        "refdef": {
          "location": [
            3.007347, 
            0
          ]
        }
      }
    }, 
    "R14": {
      "footprint": "0805", 
      "layer": "top", 
      "location": [
        -10.681661, 
        7.990113
      ], 
      "rotate": 0, 
      "show": true, 
      "silkscreen": {
        "refdef": {
          "location": [
            0, 
            0
          ]
        }
      }
    }, 
    "R15": {
      "footprint": "0805", 
      "layer": "top", 
      "location": [
        -37.766265, 
        5.45281
      ], 
      "rotate": 0, 
      "show": true, 
      "silkscreen": {
        "refdef": {
          "location": [
            2.962404, 
            0
          ]
        }
      }
    }, 
    "R16": {
      "footprint": "0805", 
      "layer": "top", 
      "location": [
        -43.710642, 
        7.989503
      ], 
      "rotate": 0, 
      "show": true, 
      "silkscreen": {
        "refdef": {
          "location": [
            3.01284, 
            0
          ]
        }
      }
    }, 
    "R17": {
      "footprint": "0805", 
      "layer": "top", 
      "location": [
        -10.681661, 
        5.45281
      ], 
      "rotate": 0, 
      "show": true, 
      "silkscreen": {
        "refdef": {
          "location": [
            0, 
            0
          ]
        }
      }
    }, 
    "R18": {
      "footprint": "0805", 
      "layer": "top", 
      "location": [
        -10.681661, 
        2.914847
      ], 
      "rotate": 0, 
      "show": true, 
      "silkscreen": {
        "refdef": {
          "location": [
            0, 
            0
          ]
        }
      }
    }, 
    "R19": {
      "footprint": "0805", 
      "layer": "top", 
      "location": [
        -10.681661, 
        0.377594
      ], 
      "rotate": 0, 
      "show": true, 
      "silkscreen": {
        "refdef": {
          "location": [
            0, 
            0
          ]
        }
      }
    }, 
    "R2": {
      "footprint": "0805", 
      "layer": "top", 
      "location": [
        -10.681661, 
        18.138665
      ], 
      "rotate": 0, 
      "show": true, 
      "silkscreen": {
        "refdef": {
          "location": [
            0, 
            0
          ]
        }
      }
    }, 
    "R20": {
      "footprint": "0805", 
      "layer": "top", 
      "location": [
        -10.681661, 
        -2.159758
      ], 
      "rotate": 0, 
      "show": true, 
      "silkscreen": {
        "refdef": {
          "location": [
            0, 
            0
          ]
        }
      }
    }, 
    "R21": {
      "footprint": "resistor-th", 
      "layer": "top", 
      "location": [
        46.830402, 
        8.751838
      ], 
      "rotate": 90, 
      "show": true, 
      "silkscreen": {
        "refdef": {
          "location": [
            0, 
            0
          ]
        }
      }
    }, 
    "R22": {
      "footprint": "0805", 
      "layer": "top", 
      "location": [
        -10.681661, 
        -4.697063
      ], 
      "rotate": 0, 
      "show": true, 
      "silkscreen": {
        "refdef": {
          "location": [
            0, 
            0
          ]
        }
      }
    }, 
    "R23": {
      "footprint": "0805", 
      "layer": "top", 
      "location": [
        -10.681661, 
        -7.234366
      ], 
      "rotate": 0, 
      "show": true, 
      "silkscreen": {
        "refdef": {
          "location": [
            0, 
            0
          ]
        }
      }
    }, 
    "R25": {
      "footprint": "0805", 
      "layer": "top", 
      "location": [
        -31.847599, 
        -9.77167
      ], 
      "rotate": 0, 
      "show": true, 
      "silkscreen": {
        "refdef": {
          "location": [
            0, 
            0
          ]
        }
      }
    }, 
    "R26": {
      "footprint": "0805", 
      "layer": "top", 
      "location": [
        -10.681661, 
        -12.308973
      ], 
      "rotate": 0, 
      "show": true, 
      "silkscreen": {
        "refdef": {
          "location": [
            0, 
            0
          ]
        }
      }
    }, 
    "R27": {
      "footprint": "0805", 
      "layer": "top", 
      "location": [
        -31.847599, 
        -12.308973
      ], 
      "rotate": 0, 
      "show": true, 
      "silkscreen": {
        "refdef": {
          "location": [
            0, 
            0
          ]
        }
      }
    }, 
    "R28": {
      "footprint": "0805", 
      "layer": "top", 
      "location": [
        -31.847599, 
        -14.846277
      ], 
      "rotate": 0, 
      "show": true, 
      "silkscreen": {
        "refdef": {
          "location": [
            0, 
            0
          ]
        }
      }
    }, 
    "R29": {
      "footprint": "0805", 
      "layer": "top", 
      "location": [
        -31.847599, 
        -17.38358
      ], 
      "rotate": 0, 
      "show": true, 
      "silkscreen": {
        "refdef": {
          "location": [
            0, 
            0
          ]
        }
      }
    }, 
    "R3": {
      "footprint": "0805", 
      "layer": "top", 
      "location": [
        -37.766265, 
        18.138665
      ], 
      "rotate": 0, 
      "show": true, 
      "silkscreen": {
        "refdef": {
          "location": [
            2.587404, 
            0
          ]
        }
      }
    }, 
    "R30": {
      "footprint": "0805", 
      "layer": "top", 
      "location": [
        -10.681661, 
        -17.38358
      ], 
      "rotate": 0, 
      "show": true, 
      "silkscreen": {
        "refdef": {
          "location": [
            0, 
            0
          ]
        }
      }
    }, 
    "R4": {
      "footprint": "0805", 
      "layer": "top", 
      "location": [
        -37.766265, 
        15.602022
      ], 
      "rotate": 0, 
      "show": true, 
      "silkscreen": {
        "refdef": {
          "location": [
            2.605348, 
            0
          ]
        }
      }
    }, 
    "R5": {
      "footprint": "0805", 
      "layer": "top", 
      "location": [
        -37.766265, 
        13.06472
      ], 
      "rotate": 0, 
      "show": true, 
      "silkscreen": {
        "refdef": {
          "location": [
            2.587404, 
            0
          ]
        }
      }
    }, 
    "R6": {
      "footprint": "0805", 
      "layer": "top", 
      "location": [
        -43.710642, 
        15.601412
      ], 
      "rotate": 0, 
      "show": true, 
      "silkscreen": {
        "refdef": {
          "location": [
            2.63784, 
            0
          ]
        }
      }
    }, 
    "R7": {
      "footprint": "0805", 
      "layer": "top", 
      "location": [
        -31.853553, 
        10.527417
      ], 
      "rotate": 0, 
      "show": true, 
      "silkscreen": {
        "refdef": {
          "location": [
            0, 
            0
          ]
        }
      }
    }, 
    "R8": {
      "footprint": "0805", 
      "layer": "top", 
      "location": [
        -10.681661, 
        13.064063
      ], 
      "rotate": 0, 
      "show": true, 
      "silkscreen": {
        "refdef": {
          "location": [
            0, 
            0
          ]
        }
      }
    }, 
    "R9": {
      "footprint": "0805", 
      "layer": "top", 
      "location": [
        -43.710642, 
        13.06411
      ], 
      "rotate": 0, 
      "show": true, 
      "silkscreen": {
        "refdef": {
          "location": [
            2.636009, 
            0
          ]
        }
      }
    }, 
    "SP1": {
      "footprint": "speaker", 
      "layer": "top", 
      "location": [
        7.324447, 
        0
      ], 
      "rotate": 0, 
      "show": true, 
      "silkscreen": {
        "refdef": {
          "location": [
            0, 
            0
          ]
        }
      }
    }
  }, 
  "config": {
    "name": "pissoff", 
    "no-docs": false, 
    "no-drill-index": false, 
    "no-flashes": false, 
    "no-layer-index": false, 
    "rev": "first", 
    "style-layout": "default", 
    "units": "mm"
  }, 
  "distances": {
    "from-pour-to": {
      "drill": 0.4, 
      "outline": 0.4, 
      "pad": 0.25, 
      "route": 0.4
    }, 
    "soldermask": {
      "circle-buffer": 0.05, 
      "path-scale": 1.05, 
      "rect-buffer": 0.05
    }, 
    "solderpaste": {
      "circle-buffer": -0.1, 
      "path-scale": 0.9, 
      "rect-buffer": -0.1
    }
  }, 
  "documentation": {
    "board-details": {
      "font-family": "Overlock-Regular-OTF-webfont", 
      "font-size": "1.5mm", 
      "letter-spacing": "0mm", 
      "line-height": "1.5mm", 
      "location": [
        -24.05914, 
        -46.206303
      ], 
      "rotate": 0, 
      "style": "fill", 
      "type": "text", 
      "value": "Board details:\nName: PissOff\nRevision: first\nDescription: \nLicense: MIT\nDesigner: Saar Drimer, Boldport, saar@boldport.com"
    }, 
    "manufacturing": {
      "font-family": "Overlock-Regular-OTF-webfont", 
      "font-size": "1.5mm", 
      "letter-spacing": "0mm", 
      "line-height": "1.5mm", 
      "location": [
        -24.075155, 
        -58.690506
      ], 
      "rotate": 0, 
      "style": "fill", 
      "type": "text", 
      "value": "Manufacturing:\nRoHS and lead free compliant manufacturing process\nUnit of length: Millimetre (mm)\nNumber of layers: 2 ('top', 'bottom')\nBoard thickness: 1.6 mm\nMaterial: FR4 35/35 um copper\nSilkscreen: top, bottom, white\nSoldermask: top, bottom, red\nSurface finish: ENIG"
    }, 
    "pcbmode": {
      "font-family": "Overlock-Regular-OTF-webfont", 
      "font-size": "1.2mm", 
      "letter-spacing": "0mm", 
      "line-height": "1.2mm", 
      "location": [
        -27.885146, 
        -69.153756
      ], 
      "rotate": 0, 
      "style": "fill", 
      "type": "text", 
      "value": "Designed with PCBmodE, an open source software\n     http://pcbmode.com\nStay updated:\n     @boldport @pcbmode http://boldport.com"
    }
  }, 
  "drill-index": {
    "location": [
      -39.873455, 
      -74.985953
    ]
  }, 
  "drills": {}, 
  "files": {
    "routing-data": "pissoff_routing.json", 
    "routing-svg": "pissoff.svg"
  }, 
  "gerber": {
    "decimals": 6, 
    "digits": 6, 
    "min-segment-length": 0.05, 
    "steps-per-segment": 100
  }, 
  "outline": {
    "shape": {
      "height": 40, 
      "radii": {
        "bl": 3, 
        "br": 3, 
        "tl": 3, 
        "tr": 3
      }, 
      "type": "path", 
      "value": "m -29.409595,-23.869438 c -1.623156,0 -2.939243,1.315502 -2.939243,2.937935 l 0,1.34455 -8.949482,0 c -1.623156,0 -2.93924,1.314964 -2.93924,2.937397 l 0,9.535467 -1.521732,0 c -1.62226,0.05384 -2.938698,1.3154998 -2.938698,2.9379351 l 0,8.3469105 c 0,1.6224353 1.315545,2.9379351 2.938698,2.9379351 l 1.521732,0 0,9.5354673 c 0.05386,1.62154 1.316084,2.937935 2.93924,2.937935 l 8.949482,0 0,1.349951 c 0.05386,1.62154 1.316084,2.937393 2.939243,2.937393 l 8.351155,0 c 1.623156,0 2.9387,-1.31496 2.9387,-2.937393 l 0,-1.349951 15.2804853,0 13.0686307,0 0,1.349951 c 0.05386,1.62154 1.316084,2.937393 2.93924,2.937393 l 8.351158,0 c 1.623156,0 2.938698,-1.31496 2.938698,-2.937393 l 0,-1.349951 8.950024,0 c 1.623156,0 2.938698,-1.315502 2.938698,-2.937935 l 0,-16.64685627 0,-16.64685873 c 0,-1.622433 -1.315542,-2.937397 -2.938698,-2.937397 l -8.950024,0 0,-1.34455 c 0,-1.622433 -1.315542,-2.937935 -2.938698,-2.937935 l -8.351158,0 c -1.623156,0 -2.93924,1.315502 -2.93924,2.937935 l 0,1.34455 -13.0686307,0 -15.2804853,0 0,-1.34455 c 0,-1.622433 -1.315544,-2.937935 -2.9387,-2.937935 l -8.351155,0 z m 77.380369,0 c -1.622261,0.05384 -2.938701,1.315499 -2.938701,2.937935 l 0,1.34455 -2.279892,0 c -1.623156,0 -2.939241,1.314964 -2.939241,2.937397 l 0,33.293715 c 0.05386,1.62154 1.316085,2.937935 2.939241,2.937935 l 2.279892,0 0,1.349951 c 0,1.622435 1.31555,2.937393 2.938701,2.937393 l 2.895501,0 c 1.623153,0 2.93924,-1.314958 2.93924,-2.937393 l 0,-1.349951 2.827459,0 c 1.623156,0 2.938698,-1.315502 2.938698,-2.937935 l 0,-4.523761 4.249831,0 c 1.623156,0 2.938699,-1.315503 2.938699,-2.9379351 l 0,-2.8942124 c 0,-1.6224325 -1.315543,-2.9373962 -2.938699,-2.9373962 l -4.249831,0 0,-6.706567 4.249831,0 c 1.623156,0 2.938699,-1.3155026 2.938699,-2.9379351 l 0,-2.8942124 c 0,-1.6224328 -1.315543,-2.9373958 -2.938699,-2.9373958 l -4.249831,0 0,-4.5243 c 0,-1.622433 -1.315545,-2.937397 -2.938698,-2.937397 l -2.827459,0 0,-1.34455 c -3e-6,-1.622436 -1.316087,-2.937935 -2.93924,-2.937935 l -2.895501,0 z", 
      "width": 80
    }
  }, 
  "shapes": {}, 
  "soldermask": {
    "circle-buffer": 0.05, 
    "path-scale": 1.05, 
    "rect-buffer": 0.05
  }, 
  "solderpaste": {
    "circle-buffer": -0.1, 
    "path-scale": 0.9, 
    "rect-buffer": -0.1
  }, 
  "stackup": {
    "name": "two-layer"
  }, 
  "vias": {
    "default-via": "VIA"
  }
}