{
  "components": {
    "B1": {
      "footprint": "battery-placeholder", 
      "layer": "bottom", 
      "location": [
        -9.313811, 
        0
      ], 
      "rotate": 180, 
      "show": true, 
      "silkscreen": {
        "refdef": {
          "location": [
            0, 
            0
          ]
        }
      }
    }, 
    "C1": {
      "footprint": "0805-cap", 
      "layer": "top", 
      "location": [
        -37.766265, 
        17.939996
      ], 
      "rotate": 0, 
      "show": true, 
      "silkscreen": {
        "refdef": {
          "location": [
            2.532497, 
            0
          ]
        }
      }
    }, 
    "C2": {
      "footprint": "0805-cap", 
      "layer": "top", 
      "location": [
        -43.710642, 
        17.939996
      ], 
      "rotate": 0, 
      "show": true, 
      "silkscreen": {
        "refdef": {
          "location": [
            2.537024, 
            0
          ]
        }
      }
    }, 
    "C3": {
      "footprint": "0805-cap", 
      "layer": "top", 
      "location": [
        -10.681661, 
        15.377142
      ], 
      "rotate": 0, 
      "show": true, 
      "silkscreen": {
        "refdef": {
          "location": [
            -3.200266, 
            0
          ]
        }
      }
    }, 
    "C4": {
      "footprint": "0805-cap", 
      "layer": "top", 
      "location": [
        -31.806824, 
        15.377142
      ], 
      "rotate": 0, 
      "show": true, 
      "silkscreen": {
        "refdef": {
          "location": [
            2.493108, 
            0
          ]
        }
      }
    }, 
    "C5": {
      "footprint": "0805-cap", 
      "layer": "top", 
      "location": [
        -10.681661, 
        -5.125714
      ], 
      "rotate": 0, 
      "show": true, 
      "silkscreen": {
        "refdef": {
          "location": [
            -3.200266, 
            0
          ]
        }
      }
    }, 
    "C6": {
      "footprint": "0805-cap", 
      "layer": "top", 
      "location": [
        -43.757371, 
        -5.125714
      ], 
      "rotate": 0, 
      "show": true, 
      "silkscreen": {
        "refdef": {
          "location": [
            0, 
            -1.493232
          ]
        }
      }
    }, 
    "C7": {
      "footprint": "0805-cap", 
      "layer": "top", 
      "location": [
        -43.757371, 
        -15.377143
      ], 
      "rotate": 0, 
      "show": true, 
      "silkscreen": {
        "refdef": {
          "location": [
            0, 
            -1.693332
          ]
        }
      }
    }, 
    "D1": {
      "footprint": "led-5mm", 
      "layer": "top", 
      "location": [
        42.330152, 
        8.941977
      ], 
      "rotate": 0, 
      "show": true, 
      "silkscreen": {
        "refdef": {
          "location": [
            0, 
            0
          ]
        }
      }
    }, 
    "D2": {
      "footprint": "led-5mm", 
      "layer": "top", 
      "location": [
        42.58832, 
        -8.527546
      ], 
      "rotate": 0, 
      "show": true, 
      "silkscreen": {
        "refdef": {
          "location": [
            0, 
            0
          ]
        }
      }
    }, 
    "D3": {
      "footprint": "0805", 
      "layer": "top", 
      "location": [
        -10.681661, 
        -17.94
      ], 
      "rotate": 0, 
      "show": true, 
      "silkscreen": {
        "refdef": {
          "location": [
            -3.205661, 
            0
          ]
        }
      }
    }, 
    "IC1": {
      "footprint": "TPA301D-SOIC8", 
      "layer": "top", 
      "location": [
        -21.853332, 
        15.357003
      ], 
      "rotate": 0, 
      "show": true, 
      "silkscreen": {
        "refdef": {
          "location": [
            0, 
            -3.693834
          ]
        }
      }
    }, 
    "IC2": {
      "footprint": "MKE04Z8VWJ4-SOIC20", 
      "layer": "top", 
      "location": [
        -21.853332, 
        1.587401
      ], 
      "rotate": 180, 
      "show": true, 
      "silkscreen": {
        "refdef": {
          "location": [
            0.0, 
            7.702122
          ]
        }
      }
    }, 
    "IC3": {
      "footprint": "LDO-fixed-TSOT-23-5", 
      "layer": "top", 
      "location": [
        -43.926362, 
        -10.251429
      ], 
      "rotate": 0, 
      "show": true, 
      "silkscreen": {
        "refdef": {
          "location": [
            0, 
            2.457879
          ]
        }
      }
    }, 
    "IC4": {
      "footprint": "SOT23-nFET", 
      "layer": "top", 
      "location": [
        -4.705088, 
        -15.377143
      ], 
      "rotate": 0, 
      "show": true, 
      "silkscreen": {
        "refdef": {
          "location": [
            0, 
            -2.257776
          ]
        }
      }
    }, 
    "J1": {
      "footprint": "1x4-2p54-stag", 
      "layer": "top", 
      "location": [
        -34.193875, 
        21.7
      ], 
      "rotate": 0, 
      "show": true, 
      "silkscreen": {
        "refdef": {
          "location": [
            6.030355, 
            -1.693332
          ]
        }
      }
    }, 
    "J10": {
      "footprint": "1x4-2p54-stag", 
      "layer": "top", 
      "location": [
        -34.193875, 
        -21.7
      ], 
      "rotate": 0, 
      "show": true, 
      "silkscreen": {
        "refdef": {
          "location": [
            5.725292, 
            1.693332
          ]
        }
      }
    }, 
    "J2": {
      "footprint": "1x4-2p54-stag", 
      "layer": "top", 
      "location": [
        8.172962, 
        21.7
      ], 
      "rotate": 0, 
      "show": true, 
      "silkscreen": {
        "refdef": {
          "location": [
            6.266058, 
            -1.693332
          ]
        }
      }
    }, 
    "J3": {
      "footprint": "1x6-2p54-stag", 
      "layer": "top", 
      "location": [
        -51.04444, 
        10.724445
      ], 
      "rotate": 90, 
      "show": true, 
      "silkscreen": {
        "refdef": {
          "rotate": -90, 
          "location": [
            8.466667, 
            -0.0
          ]
        }
      }
    }, 
    "J4": {
      "footprint": "solder-blob-jumper", 
      "layer": "top", 
      "location": [
        -43.710642, 
        2.563517
      ], 
      "rotate": 0, 
      "show": true, 
      "silkscreen": {
        "refdef": {
          "location": [
            -2.257778,
            0
          ]
        }
      }
    }, 
    "J5": {
      "footprint": "interface-holes", 
      "layer": "top", 
      "location": [
        33.471123, 
        0
      ], 
      "rotate": 0, 
      "show": true, 
      "silkscreen": {
        "refdef": {
          "location": [
            0, 
            0
          ]
        }
      }
    }, 
    "J6": {
      "footprint": "interface-holes-main-board", 
      "layer": "top", 
      "location": [
        24.6, 
        0
      ], 
      "rotate": 0, 
      "show": true, 
      "silkscreen": {
        "refdef": {
          "location": [
            0, 
            0
          ]
        }
      }
    }, 
    "J7": {
      "footprint": "1x6-2p54-stag", 
      "layer": "top", 
      "location": [
        -51.04444, 
        -10.724445
      ], 
      "rotate": 90, 
      "show": true, 
      "silkscreen": {
        "refdef": {
          "rotate": -90, 
          "location": [
            -8.523839, 
            0.0
          ]
        }
      }
    }, 
    "J8": {
      "footprint": "microSD-molex-105162-001", 
      "layer": "top", 
      "location": [
        -21.853332, 
        -17.728305
      ], 
      "rotate": 0, 
      "show": true, 
      "silkscreen": {
        "refdef": {
          "location": [
            0, 
            -0.786787
          ]
        }
      }
    }, 
    "J9": {
      "footprint": "1x4-2p54-stag", 
      "layer": "top", 
      "location": [
        8.172962, 
        -21.7
      ], 
      "rotate": 0, 
      "show": true, 
      "silkscreen": {
        "refdef": {
          "location": [
            6.269527, 
            1.693332
          ]
        }
      }
    }, 
    "R1": {
      "footprint": "0805", 
      "layer": "top", 
      "location": [
        -31.821886, 
        17.940655
      ], 
      "rotate": 0, 
      "show": true, 
      "silkscreen": {
        "refdef": {
          "location": [
            2.431133, 
            0
          ]
        }
      }
    }, 
    "R10": {
      "footprint": "0805", 
      "layer": "top", 
      "location": [
        -37.766265, 
        10.251428
      ], 
      "rotate": 0, 
      "show": true, 
      "silkscreen": {
        "refdef": {
          "location": [
            2.861941, 
            0
          ]
        }
      }
    }, 
    "R11": {
      "footprint": "0805", 
      "layer": "top", 
      "location": [
        -43.710642, 
        10.252087
      ], 
      "rotate": 0, 
      "show": true, 
      "silkscreen": {
        "refdef": {
          "location": [
            2.85155, 
            0
          ]
        }
      }
    }, 
    "R12": {
      "footprint": "0805", 
      "layer": "top", 
      "location": [
        -10.681661, 
        10.251428
      ], 
      "rotate": 0, 
      "show": true, 
      "silkscreen": {
        "refdef": {
          "location": [
            -2.879392, 
            0
          ]
        }
      }
    }, 
    "R13": {
      "footprint": "resistor-th", 
      "layer": "top", 
      "location": [
        46.830402, 
        8.751838
      ], 
      "rotate": 90, 
      "show": true, 
      "silkscreen": {
        "refdef": {
          "location": [
            0, 
            0
          ]
        }
      }
    }, 
    "R14": {
      "footprint": "0805", 
      "layer": "top", 
      "location": [
        -10.681661, 
        7.689231
      ], 
      "rotate": 0, 
      "show": true, 
      "silkscreen": {
        "refdef": {
          "location": [
            -2.865744, 
            0
          ]
        }
      }
    }, 
    "R15": {
      "footprint": "0805", 
      "layer": "top", 
      "location": [
        -43.710642, 
        7.689231
      ], 
      "rotate": 0, 
      "show": true, 
      "silkscreen": {
        "refdef": {
          "location": [
            2.854089, 
            0
          ]
        }
      }
    }, 
    "R16": {
      "footprint": "0805", 
      "layer": "top", 
      "location": [
        -37.766265, 
        7.68862
      ], 
      "rotate": 0, 
      "show": true, 
      "silkscreen": {
        "refdef": {
          "location": [
            2.858767, 
            0
          ]
        }
      }
    }, 
    "R17": {
      "footprint": "0805", 
      "layer": "top", 
      "location": [
        -10.681661, 
        5.126371
      ], 
      "rotate": 0, 
      "show": true, 
      "silkscreen": {
        "refdef": {
          "location": [
            -2.872726, 
            0
          ]
        }
      }
    }, 
    "R18": {
      "footprint": "0805", 
      "layer": "top", 
      "location": [
        -10.681661, 
        2.562857
      ], 
      "rotate": 0, 
      "show": true, 
      "silkscreen": {
        "refdef": {
          "location": [
            -2.876535, 
            0
          ]
        }
      }
    }, 
    "R19": {
      "footprint": "0805", 
      "layer": "top", 
      "location": [
        -10.681661, 
        0
      ], 
      "rotate": 0, 
      "show": true, 
      "silkscreen": {
        "refdef": {
          "location": [
            -2.878122, 
            0
          ]
        }
      }
    }, 
    "R2": {
      "footprint": "0805", 
      "layer": "top", 
      "location": [
        -10.681661, 
        17.939996
      ], 
      "rotate": 0, 
      "show": true, 
      "silkscreen": {
        "refdef": {
          "location": [
            -3.204392, 
            0
          ]
        }
      }
    }, 
    "R20": {
      "footprint": "0805", 
      "layer": "top", 
      "location": [
        -10.681661, 
        -2.562858
      ], 
      "rotate": 0, 
      "show": true, 
      "silkscreen": {
        "refdef": {
          "location": [
            -2.873361, 
            0
          ]
        }
      }
    }, 
    "R21": {
      "footprint": "0805", 
      "layer": "top", 
      "location": [
        -10.681661, 
        -7.688571
      ], 
      "rotate": 0, 
      "show": true, 
      "silkscreen": {
        "refdef": {
          "location": [
            -2.883835, 
            0
          ]
        }
      }
    }, 
    "R22": {
      "footprint": "0805", 
      "layer": "top", 
      "location": [
        -10.681661, 
        -10.251429
      ], 
      "rotate": 0, 
      "show": true, 
      "silkscreen": {
        "refdef": {
          "location": [
            -2.879392, 
            0
          ]
        }
      }
    }, 
    "R23": {
      "footprint": "0805", 
      "layer": "top", 
      "location": [
        24.349311, 
        -12.814285
      ], 
      "rotate": 0, 
      "show": true, 
      "silkscreen": {
        "refdef": {
          "location": [
            -2.862646, 
            0
          ]
        }
      }
    }, 
    "R24": {
      "footprint": "0805", 
      "layer": "top", 
      "location": [
        -10.681661, 
        -12.814285
      ], 
      "rotate": 0, 
      "show": true, 
      "silkscreen": {
        "refdef": {
          "location": [
            -2.865744, 
            0
          ]
        }
      }
    }, 
    "R25": {
      "footprint": "0805", 
      "layer": "top", 
      "location": [
        -10.650184, 
        -15.377143
      ], 
      "rotate": 0, 
      "show": true, 
      "silkscreen": {
        "refdef": {
          "location": [
            -2.912773, 
            0
          ]
        }
      }
    }, 
    "R26": {
      "footprint": "0805", 
      "layer": "top", 
      "location": [
        24.349311, 
        -15.377143
      ], 
      "rotate": 0, 
      "show": true, 
      "silkscreen": {
        "refdef": {
          "location": [
            -2.862646, 
            0
          ]
        }
      }
    }, 
    "R27": {
      "footprint": "0805", 
      "layer": "top", 
      "location": [
        24.349311, 
        -17.94
      ], 
      "rotate": 0, 
      "show": true, 
      "silkscreen": {
        "refdef": {
          "location": [
            -2.862646, 
            0
          ]
        }
      }
    }, 
    "R3": {
      "footprint": "0805", 
      "layer": "top", 
      "location": [
        -37.766265, 
        15.377142
      ], 
      "rotate": 0, 
      "show": true, 
      "silkscreen": {
        "refdef": {
          "location": [
            2.529006, 
            0
          ]
        }
      }
    }, 
    "R4": {
      "footprint": "0805", 
      "layer": "top", 
      "location": [
        -43.710642, 
        15.377801
      ], 
      "rotate": 0, 
      "show": true, 
      "silkscreen": {
        "refdef": {
          "location": [
            2.544641, 
            0
          ]
        }
      }
    }, 
    "R5": {
      "footprint": "0805", 
      "layer": "top", 
      "location": [
        -31.853553, 
        12.814944
      ], 
      "rotate": 0, 
      "show": true, 
      "silkscreen": {
        "refdef": {
          "location": [
            2.518255, 
            0
          ]
        }
      }
    }, 
    "R6": {
      "footprint": "0805", 
      "layer": "top", 
      "location": [
        -37.766265, 
        12.814334
      ], 
      "rotate": 0, 
      "show": true, 
      "silkscreen": {
        "refdef": {
          "location": [
            2.533767, 
            0
          ]
        }
      }
    }, 
    "R7": {
      "footprint": "0805", 
      "layer": "top", 
      "location": [
        -43.710642, 
        12.814944
      ], 
      "rotate": 0, 
      "show": true, 
      "silkscreen": {
        "refdef": {
          "location": [
            2.537659, 
            0
          ]
        }
      }
    }, 
    "R8": {
      "footprint": "0805", 
      "layer": "top", 
      "location": [
        -10.681661, 
        12.814285
      ], 
      "rotate": 0, 
      "show": true, 
      "silkscreen": {
        "refdef": {
          "location": [
            -3.201535, 
            0
          ]
        }
      }
    }, 
    "R9": {
      "footprint": "0805", 
      "layer": "top", 
      "location": [
        -31.853553, 
        10.251477
      ], 
      "rotate": 0, 
      "show": true, 
      "silkscreen": {
        "refdef": {
          "location": [
            2.521429, 
            0
          ]
        }
      }
    }, 
    "SP1": {
      "footprint": "speaker", 
      "layer": "top", 
      "location": [
        7.324447, 
        0
      ], 
      "rotate": 0, 
      "show": true, 
      "silkscreen": {
        "refdef": {
          "location": [
            0, 
            0
          ]
        }
      }
    }
  }, 
  "config": {
    "name": "pissoff", 
    "no-docs": false, 
    "no-drill-index": false, 
    "no-flashes": false, 
    "no-layer-index": false, 
    "rev": "first", 
    "style-layout": "default", 
    "units": "mm"
  }, 
  "distances": {
    "from-pour-to": {
      "drill": 0.4, 
      "outline": 0.3, 
      "pad": 0.2, 
      "route": 0.2
    }, 
    "soldermask": {
      "circle-buffer": 0.05, 
      "path-scale": 1.05, 
      "rect-buffer": 0.05
    }, 
    "solderpaste": {
      "circle-buffer": -0.1, 
      "path-scale": 0.9, 
      "rect-buffer": -0.1
    }
  }, 
  "documentation": {
    "board-details": {
      "font-family": "Overlock-Regular-OTF-webfont", 
      "font-size": "1.5mm", 
      "letter-spacing": "0mm", 
      "line-height": "1.5mm", 
      "location": [
        -41.68511, 
        -30.197393
      ], 
      "rotate": 0, 
      "style": "fill", 
      "type": "text", 
      "value": "Board details:\nName: PissOff\nRevision: first\nDescription: \nLicense: MIT\nDesigner: Saar Drimer, Boldport, saar@boldport.com"
    }, 
    "manufacturing": {
      "font-family": "Overlock-Regular-OTF-webfont", 
      "font-size": "1.5mm", 
      "letter-spacing": "0mm", 
      "line-height": "1.5mm", 
      "location": [
        -41.701125, 
        -42.681596
      ], 
      "rotate": 0, 
      "style": "fill", 
      "type": "text", 
      "value": "Manufacturing:\nRoHS and lead free compliant manufacturing process\nUnit of length: Millimetre (mm)\nNumber of layers: 2 ('top', 'bottom')\nBoard thickness: 1.6 mm\nMaterial: FR4 35/35 um copper\nSilkscreen: top, bottom, white\nSoldermask: top, bottom, red\nSurface finish: ENIG"
    }, 
    "pcbmode": {
      "font-family": "Overlock-Regular-OTF-webfont", 
      "font-size": "1.2mm", 
      "letter-spacing": "0mm", 
      "line-height": "1.2mm", 
      "location": [
        -45.511116, 
        -53.144846
      ], 
      "rotate": 0, 
      "style": "fill", 
      "type": "text", 
      "value": "Designed with PCBmodE, an open source software\n     http://pcbmode.com\nStay updated:\n     @boldport @pcbmode http://boldport.com"
    }
  }, 
  "drill-index": {
    "location": [
      -57.499425, 
      -58.977043
    ]
  }, 
  "drills": {}, 
  "files": {
    "routing-data": "pissoff_routing.json", 
    "routing-svg": "pissoff.svg"
  }, 
  "gerber": {
    "decimals": 6, 
    "digits": 6, 
    "min-segment-length": 0.05, 
    "steps-per-segment": 100
  }, 
  "outline": {
    "shape": {
      "height": 40, 
      "radii": {
        "bl": 3, 
        "br": 3, 
        "tl": 3, 
        "tr": 3
      }, 
      "type": "path", 
      "value": "m -29.409595,-23.869438 c -1.623156,0 -2.939243,1.315502 -2.939243,2.937935 l 0,1.34455 -8.949482,0 c -1.623156,0 -2.93924,1.314964 -2.93924,2.937397 l 0,9.535467 -1.521732,0 c -1.62226,0.05384 -2.938698,1.3154998 -2.938698,2.9379351 l 0,8.3469105 c 0,1.6224353 1.315545,2.9379351 2.938698,2.9379351 l 1.521732,0 0,9.5354673 c 0.05386,1.62154 1.316084,2.937935 2.93924,2.937935 l 8.949482,0 0,1.349951 c 0.05386,1.62154 1.316084,2.937393 2.939243,2.937393 l 8.351155,0 c 1.623156,0 2.9387,-1.31496 2.9387,-2.937393 l 0,-1.349951 15.2804853,0 13.0686307,0 0,1.349951 c 0.05386,1.62154 1.316084,2.937393 2.93924,2.937393 l 8.351158,0 c 1.623156,0 2.938698,-1.31496 2.938698,-2.937393 l 0,-1.349951 8.950024,0 c 1.623156,0 2.938698,-1.315502 2.938698,-2.937935 l 0,-16.64685627 0,-16.64685873 c 0,-1.622433 -1.315542,-2.937397 -2.938698,-2.937397 l -8.950024,0 0,-1.34455 c 0,-1.622433 -1.315542,-2.937935 -2.938698,-2.937935 l -8.351158,0 c -1.623156,0 -2.93924,1.315502 -2.93924,2.937935 l 0,1.34455 -13.0686307,0 -15.2804853,0 0,-1.34455 c 0,-1.622433 -1.315544,-2.937935 -2.9387,-2.937935 l -8.351155,0 z m 77.380369,0 c -1.622261,0.05384 -2.938701,1.315499 -2.938701,2.937935 l 0,1.34455 -2.279892,0 c -1.623156,0 -2.939241,1.314964 -2.939241,2.937397 l 0,33.293715 c 0.05386,1.62154 1.316085,2.937935 2.939241,2.937935 l 2.279892,0 0,1.349951 c 0,1.622435 1.31555,2.937393 2.938701,2.937393 l 2.895501,0 c 1.623153,0 2.93924,-1.314958 2.93924,-2.937393 l 0,-1.349951 2.827459,0 c 1.623156,0 2.938698,-1.315502 2.938698,-2.937935 l 0,-4.523761 4.249831,0 c 1.623156,0 2.938699,-1.315503 2.938699,-2.9379351 l 0,-2.8942124 c 0,-1.6224325 -1.315543,-2.9373962 -2.938699,-2.9373962 l -4.249831,0 0,-6.706567 4.249831,0 c 1.623156,0 2.938699,-1.3155026 2.938699,-2.9379351 l 0,-2.8942124 c 0,-1.6224328 -1.315543,-2.9373958 -2.938699,-2.9373958 l -4.249831,0 0,-4.5243 c 0,-1.622433 -1.315545,-2.937397 -2.938698,-2.937397 l -2.827459,0 0,-1.34455 c -3e-6,-1.622436 -1.316087,-2.937935 -2.93924,-2.937935 l -2.895501,0 z", 
      "width": 80
    }
  }, 
  "shapes": {
    "LUCKY": {
      "footprint": "lucky-resistor-logo", 
      "layer": "top", 
      "location": [
        -100, 
        0
      ], 
      "scale": 0.3, 
      "show": true
    }, 
    "POURS": {
      "footprint": "pours", 
      "layer": "top", 
      "location": [
        0, 
        0
      ], 
      "show": true
    }, 
    "PWR-LGND": {
      "footprint": "power-header-legend", 
      "layer": "top", 
      "location": [
        -47.8376, 
        -10.724445
      ], 
      "scale": 1, 
      "show": true
    }, 
    "UART-LGND": {
      "footprint": "uart-header-legend", 
      "layer": "top", 
      "location": [
        -48.20852, 
        9.334595
      ], 
      "scale": 1, 
      "show": true
    }
  }, 
  "soldermask": {
    "circle-buffer": 0.05, 
    "path-scale": 1.05, 
    "rect-buffer": 0.05
  }, 
  "solderpaste": {
    "circle-buffer": -0.1, 
    "path-scale": 0.9, 
    "rect-buffer": -0.1
  }, 
  "stackup": {
    "name": "two-layer"
  }, 
  "vias": {
    "default-via": "VIA"
  }
}
